SPARQLTransformer.py
SPARQLTransformer-2.4.0.data/data/txt/requirements.txt
SPARQLTransformer-2.4.0.dist-info/LICENSE
SPARQLTransformer-2.4.0.dist-info/METADATA
SPARQLTransformer-2.4.0.dist-info/WHEEL
SPARQLTransformer-2.4.0.dist-info/top_level.txt
SPARQLTransformer-2.4.0.dist-info/RECORD
