Metadata-Version: 2.1
Name: SPARQLTransformer
Version: 2.4.0
Summary: Write your SPARQL query directly in the JSON-LD you would like to have in output
Home-page: https://github.com/D2KLab/py-sparql-transformer
Author: Pasquale Lisena
Author-email: pasquale.lisena@eurecom.fr
License: Apache 2.0
Project-URL: Bug Tracker, https://github.com/D2KLab/py-sparql-transformer/issues
Project-URL: Documentation, https://github.com/D2KLab/py-sparql-transformer
Project-URL: Source Code, https://github.com/D2KLab/py-sparql-transformer
Keywords: sparql json json-ld semantic
License-File: LICENSE
Requires-Dist: SPARQLWrapper
Requires-Dist: simplejson
